[{
    "socialmedia": "facebook",
    "engagement": [{
        "lvl": 0,
        "time": [{
                "weekday": 0 ,
                "starthour": 18,
                "endhour": 8 
            }, 
            {
                "weekday": 1 ,
                "starthour": 22,
                "endhour": 5
            }, 
            {
                "weekday": 2 ,
                "starthour": 22,
                "endhour": 4
            }, 
            {
                "weekday": 3 ,
                "starthour": 22,
                "endhour": 3
            }, 
            {
                "weekday": 4 ,
                "starthour": 22,
                "endhour": 4
            }, 
            {
                "weekday": 5 ,
                "starthour": 22,
                "endhour": 4
            }, 
            {
                "weekday": 6 ,
                "starthour": 18,
                "endhour": 7
            }

        ]
    },
    {
        "lvl": 1,
        "time": [{
                "weekday": 0 ,
                "starthour": 8,
                "endhour": 18
            }, 
            {
                "weekday": 1 ,
                "starthour": 5,
                "endhour": 8
            }, 
            {
                "weekday": 1 ,
                "starthour": 18,
                "endhour": 22
            }, 
            {
                "weekday": 2 ,
                "starthour": 4,
                "endhour": 8
            }, 
            {
                "weekday": 2 ,
                "starthour": 18,
                "endhour": 22
            }, 
            {
                "weekday": 3 ,
                "starthour": 3,
                "endhour": 7
            }, 
            {
                "weekday": 3 ,
                "starthour": 18,
                "endhour": 22
            }, 
            {
                "weekday": 4 ,
                "starthour": 4,
                "endhour": 8
            }, 
            {
                "weekday": 4 ,
                "starthour": 18,
                "endhour": 22
            }, 
            {
                "weekday": 5 ,
                "starthour": 4,
                "endhour": 7
            }, 
            {
                "weekday": 5 ,
                "starthour": 16,
                "endhour": 22
            }, 
            {
                "weekday": 6 ,
                "starthour": 18,
                "endhour": 22
            }

        ]
    },
    {
        "lvl": 2,
        "time": [{
                "weekday": 1 ,
                "starthour": 8,
                "endhour": 16
            }, 
            {
                "weekday": 2 ,
                "starthour": 8,
                "endhour": 13
            }, 
            {
                "weekday": 2 ,
                "starthour": 15,
                "endhour": 18
            }, 
            {
                "weekday": 3 ,
                "starthour": 7,
                "endhour": 9
            }, 
            {
                "weekday": 3 ,
                "starthour": 16,
                "endhour": 18
            }, 
            {
                "weekday": 4 ,
                "starthour": 8,
                "endhour": 9
            }, 
            {
                "weekday": 5 ,
                "starthour": 7,
                "endhour": 9
            }, 
            {
                "weekday": 5 ,
                "starthour": 12,
                "endhour": 16
            }

        ]
    },
    {
        "lvl": 3,
        "time": [{
                "weekday": 2 ,
                "starthour": 13,
                "endhour": 15
            }, 
            {
                "weekday": 3 ,
                "starthour": 9,
                "endhour": 16
            }, 
            {
                "weekday": 4 ,
                "starthour": 9,
                "endhour": 15
            }, 
            {
                "weekday": 5 ,
                "starthour": 9,
                "endhour": 15
            }
            
        ]
    }]

},
{
    "socialmedia": "instagram",
    "engagement": [{
        "lvl": 0,
        "time": [{
                "weekday": 0 ,
                "starthour": 15,
                "endhour": 7
            }, 
            {
                "weekday": 1 ,
                "starthour": 22,
                "endhour": 7
            }, 
            {
                "weekday": 2 ,
                "starthour": 22,
                "endhour": 6
            }, 
            {
                "weekday": 3 ,
                "starthour": 22,
                "endhour": 5
            }, 
            {
                "weekday": 4 ,
                "starthour": 22,
                "endhour": 4
            }, 
            {
                "weekday": 5 ,
                "starthour": 22,
                "endhour": 5
            }, 
            {
                "weekday": 6 ,
                "starthour": 17,
                "endhour": 7
            }

        ]
    },
    {
        "lvl": 1,
        "time": [{
                "weekday": 0 ,
                "starthour": 7,
                "endhour": 15
            }, 
            {
                "weekday": 1 ,
                "starthour": 7,
                "endhour": 11
            }, 
            {
                "weekday": 1 ,
                "starthour": 3,
                "endhour": 22
            }, 
            {
                "weekday": 2 ,
                "starthour": 6,
                "endhour": 10
            }, 
            {
                "weekday": 2 ,
                "starthour": 16,
                "endhour": 17
            }, 
            {
                "weekday": 2 ,
                "starthour": 20,
                "endhour": 22
            }, 
            {
                "weekday": 3 ,
                "starthour": 5,
                "endhour": 8
            }, 
            {
                "weekday": 3 ,
                "starthour": 18,
                "endhour": 22
            }, 
            {
                "weekday": 4 ,
                "starthour": 4,
                "endhour": 9
            }, 
            {
                "weekday": 4 ,
                "starthour": 17,
                "endhour": 18
            }, 
            {
                "weekday": 4 ,
                "starthour": 20,
                "endhour": 22
            }, 
            {
                "weekday": 5 ,
                "starthour": 5,
                "endhour": 8
            }, 
            {
                "weekday": 5 ,
                "starthour": 17,
                "endhour": 22
            }, 
            {
                "weekday": 6 ,
                "starthour": 7,
                "endhour": 10
            },
            {
                "weekday": 6 ,
                "starthour": 11,
                "endhour": 17
            }

        ]
    },
    {
        "lvl": 2,
        "time": [{
                "weekday": 1 ,
                "starthour": 11,
                "endhour": 15
            }, 
            {
                "weekday": 2 ,
                "starthour": 10,
                "endhour": 16
            }, 
            {
                "weekday": 2 ,
                "starthour": 17,
                "endhour": 20
            }, 
            {
                "weekday": 3 ,
                "starthour": 8,
                "endhour": 11
            }, 
            {
                "weekday": 3 ,
                "starthour": 12,
                "endhour": 18
            }, 
            {
                "weekday": 4 ,
                "starthour": 9,
                "endhour": 17
            }, 
            {
                "weekday": 4 ,
                "starthour": 18,
                "endhour": 20
            }, 
            {
                "weekday": 5 ,
                "starthour": 8,
                "endhour": 10
            },
            {
                "weekday": 5 ,
                "starthour": 12,
                "endhour": 17
            },
            {
                "weekday": 6 ,
                "starthour": 10,
                "endhour": 11 
            }

        ]
    },
    {
        "lvl": 3,
        "time": [{
                "weekday": 3 ,
                "starthour": 11,
                "endhour": 12
            }, 
            {
                "weekday": 5 ,
                "starthour": 9,
                "endhour": 12
            }
        ]
    }]

},
{
    "socialmedia": "twitter",
    "engagement": [{
        "lvl": 0,
        "time": [{
                "weekday": 0 ,
                "starthour": 21,
                "endhour": 8 
            }, 
            {
                "weekday": 1 ,
                "starthour": 20,
                "endhour": 6
            }, 
            {
                "weekday": 2 ,
                "starthour":21,
                "endhour": 6
            }, 
            {
                "weekday": 3 ,
                "starthour": 21,
                "endhour": 6
            }, 
            {
                "weekday": 4 ,
                "starthour": 21,
                "endhour": 6
            }, 
            {
                "weekday": 5 ,
                "starthour": 18,
                "endhour": 5
            }, 
            {
                "weekday": 6 ,
                "starthour": 16,
                "endhour": 8
            }

        ]
    },
    {
        "lvl": 1,
        "time": [{
                "weekday": 0 ,
                "starthour": 8,
                "endhour": 9
            }, 
            {
                "weekday": 0 ,
                "starthour": 10,
                "endhour": 21
            }, 
            {
                "weekday": 1,
                "starthour": 6,
                "endhour": 9
            }, 
            {
                "weekday": 1,
                "starthour": 14,
                "endhour": 20
            }, 
            {
                "weekday": 2,
                "starthour": 6,
                "endhour": 9
            }, 
            {
                "weekday": 2,
                "starthour": 17,
                "endhour": 19
            }, 
            {
                "weekday": 3,
                "starthour": 6,
                "endhour": 7
            }, 
            {
                "weekday": 3 ,
                "starthour": 17,
                "endhour": 21
            }, 
            {
                "weekday": 4 ,
                "starthour": 6,
                "endhour": 9
            }, 
            {
                "weekday": 4 ,
                "starthour": 13,
                "endhour": 21
            }, 
            {
                "weekday": 5 ,
                "starthour": 5,
                "endhour": 7
            }, 
            {
                "weekday": 5 ,
                "starthour": 16,
                "endhour": 18
            }, 
            {
                "weekday": 6 ,
                "starthour": 8,
                "endhour": 9
            },
            {
                "weekday": 6 ,
                "starthour": 11,
                "endhour": 17
            }
        ]
    },
    {
        "lvl": 2,
        "time": [{
                "weekday": 0 ,
                "starthour": 9,
                "endhour": 10
            }, 
            {
                "weekday": 1 ,
                "starthour": 11,
                "endhour": 14
            }, 
            {
                "weekday": 2 ,
                "starthour": 12,
                "endhour": 17
            }, 
            {
                "weekday": 2 ,
                "starthour": 19,
                "endhour": 21
            }, 
            {
                "weekday": 3 ,
                "starthour": 7,
                "endhour": 9
            }, 
            {
                "weekday": 3 ,
                "starthour": 15,
                "endhour": 21
            }, 
            {
                "weekday": 4 ,
                "starthour": 10,
                "endhour": 13
            }, 
            {
                "weekday": 5 ,
                "starthour": 7,
                "endhour": 8
            }, 
            {
                "weekday": 5 ,
                "starthour": 12,
                "endhour": 16
            },
            {
                "weekday": 6 ,
                "starthour": 9,
                "endhour": 11
            }
    

        ]
    },
    {
        "lvl": 3,
        "time": [{
                "weekday": 2 ,
                "starthour": 9,
                "endhour": 12
            }, 
            {
                "weekday": 3 ,
                "starthour": 9,
                "endhour": 15
            }, 
            {
                "weekday": 4 ,
                "starthour": 9,
                "endhour": 10
            }, 
            {
                "weekday": 5 ,
                "starthour": 8,
                "endhour": 12
            }
            
        ]
    }]

}
]



